sbx_sentence_sentiment_kb_sent/__init__.py
sbx_sentence_sentiment_kb_sent/annotations.py
sbx_sentence_sentiment_kb_sent/constants.py
sbx_sentence_sentiment_kb_sent/metadata.yaml
sbx_sentence_sentiment_kb_sent/py.typed
sbx_sentence_sentiment_kb_sent/sentiment_analyzer.py
sparv_sbx_sentence_sentiment_kb_sent-0.3.1.dist-info/METADATA
sparv_sbx_sentence_sentiment_kb_sent-0.3.1.dist-info/WHEEL
sparv_sbx_sentence_sentiment_kb_sent-0.3.1.dist-info/entry_points.txt
sparv_sbx_sentence_sentiment_kb_sent-0.3.1.dist-info/RECORD
